LICENSE
README.md
setup.py
pyFBIG/__init__.py
pyFBIG/cpf_generator.py
pyFBIG/cpf_product.py
pyFBIG/crm_generator.py
pyFBIG/crm_product.py
pyFBIG/fake_br_id.py
pyFBIG/igen_product.py
pyFBIG/igenerator.py
pyFBIG/rg_generator.py
pyFBIG/rg_product.py
pyFBIG.egg-info/PKG-INFO
pyFBIG.egg-info/SOURCES.txt
pyFBIG.egg-info/dependency_links.txt
pyFBIG.egg-info/top_level.txt
tests/test_fake_br_id.py
tests/test_gen_cpf.py
tests/test_gen_crm.py
tests/test_gen_rg.py